src/__init__.py
src/main.py
ner_reformat-1.0.0.dist-info/LICENSE
ner_reformat-1.0.0.dist-info/METADATA
ner_reformat-1.0.0.dist-info/WHEEL
ner_reformat-1.0.0.dist-info/top_level.txt
ner_reformat-1.0.0.dist-info/RECORD
