Metadata-Version: 2.1
Name: ner-reformat
Version: 1.0.0
Summary: A Python package for converting various Named Entity Recognition (NER) formats to BRAT and BIO formats.
Home-page: https://github.com/project178/ner_reformat
Author: MB
Author-email: mariya.borovikova@universite-paris-saclay.fr
Keywords: NLP Named Entity Recognition annotation NER BRAT BIO
Classifier: Development Status :: 3 - Alpha
Classifier: License :: OSI Approved :: MIT License
Classifier: Programming Language :: Python :: 3
Classifier: Programming Language :: Python :: 3.7
Classifier: Programming Language :: Python :: 3.8
Classifier: Programming Language :: Python :: 3.9
Classifier: Programming Language :: Python :: 3.10
Classifier: Programming Language :: Python :: 3.11
Classifier: Programming Language :: Python :: 3.12
Requires-Python: >=3.7
License-File: LICENSE
Requires-Dist: regex
Requires-Dist: requests
Requires-Dist: beautifulsoup4
Requires-Dist: tqdm
Requires-Dist: torch
Requires-Dist: bioc
Requires-Dist: joblib
